hello.py
maxez-0.0.2.dist-info/METADATA
maxez-0.0.2.dist-info/WHEEL
maxez-0.0.2.dist-info/top_level.txt
maxez-0.0.2.dist-info/RECORD
