Metadata-Version: 2.1
Name: maxez
Version: 0.0.2
Summary: Math Package
Home-page: UNKNOWN
License: UNKNOWN
Platform: UNKNOWN
